bces/__init__.py
bces/bces.py
bces-1.5.1.dist-info/LICENSE
bces-1.5.1.dist-info/METADATA
bces-1.5.1.dist-info/WHEEL
bces-1.5.1.dist-info/top_level.txt
bces-1.5.1.dist-info/RECORD
