Metadata-Version: 2.1
Name: bces
Version: 1.5.1
Summary: Python module for performing linear regression for data with measurement errors and intrinsic scatter
Home-page: https://github.com/rsnemmen/BCES
Download-URL: https://github.com/rsnemmen/BCES/archive/1.5.1.tar.gz
Author: Rodrigo Nemmen
Author-email: rodrigo.nemmen@iag.usp.br
License: MIT License
Keywords: statistics,fitting,linear-regression,machine-learning
License-File: LICENSE
